easy_as_pypi_getver/__init__.py
easy_as_pypi_getver-1.0.5.dist-info/LICENSE
easy_as_pypi_getver-1.0.5.dist-info/METADATA
easy_as_pypi_getver-1.0.5.dist-info/WHEEL
easy_as_pypi_getver-1.0.5.dist-info/RECORD
